Metadata-Version: 2.1
Name: exif-delete
Version: 0.9.8
Summary: A simple commandline tool to remove the EXIF data from image files.
Home-page: https://github.com/theJollySin/exif_delete
Author: John Stilley
License: GPLv3
Keywords: tool security privacy images exif
Platform: UNKNOWN
Classifier: Development Status :: 4 - Beta
Classifier: Environment :: Console
Classifier: License :: OSI Approved :: GNU General Public License v3 (GPLv3)
Classifier: Operating System :: OS Independent
Classifier: Programming Language :: Python :: 3.4
Classifier: Programming Language :: Python :: 3.5
Classifier: Programming Language :: Python :: 3.6
Classifier: Programming Language :: Python :: 3.7
Classifier: Topic :: Utilities
Classifier: Topic :: Security
Classifier: Topic :: Software Development :: Libraries :: Python Modules
Classifier: Natural Language :: English
